<?xml version="1.0" encoding="UTF-8"?>
<bulkCmConfigDataFile xmlns:es="EricssonSpecificAttributes.17.28.xsd"
    xmlns:un="utranNrm.xsd" xmlns:xn="genericNrm.xsd"
    xmlns:gn="geranNrm.xsd" xmlns="configData.xsd">
    <fileHeader fileFormatVersion="32.615 V4.5" vendorName="Ericsson"/>
    <configData dnPrefix="Undefined">
        <xn:SubNetwork id="ONRM_RootMo_R">
            <xn:SubNetwork id="eNB_CH">
                <xn:MeContext id="RN_CH0001">
                    <xn:ManagedElement id="RN_CH0001">
                        <xn:VsDataContainer id="1">
                            <xn:attributes>
                                <xn:vsDataType>vsDataENodeBFunction</xn:vsDataType>
                                <xn:vsDataFormatVersion>EricssonSpecificAttributes.17.28</xn:vsDataFormatVersion>
                                <es:vsDataENodeBFunction/>
                            </xn:attributes>
                            <xn:VsDataContainer id="1">
                                <xn:attributes>
                                    <xn:vsDataType>vsDataSectorCarrier</xn:vsDataType>
                                    <xn:vsDataFormatVersion>EricssonSpecificAttributes.17.28</xn:vsDataFormatVersion>
                                    <es:vsDataSectorCarrier>
                                    <es:noOfTxAntennas>2</es:noOfTxAntennas>
                                    <es:maximumTransmissionPower>457</es:maximumTransmissionPower>
                                    <es:prsEnabled>true</es:prsEnabled>
                                    <es:rfBranchTxRef></es:rfBranchTxRef>
                                    <es:noOfRxAntennas>2</es:noOfRxAntennas>
                                    <es:rfBranchRxRef></es:rfBranchRxRef>
                                    <es:ulForcedTimingAdvanceCommand>0</es:ulForcedTimingAdvanceCommand>
                                    <es:reservedBy>SubNetwork=ONRM_RootMo_R,SubNetwork=eNB_CH,MeContext=RN_CH0001,ManagedElement=RN_CH0001,vsDataENodeBFunction=1,vsDataEUtranCellFDD=CH0001L13</es:reservedBy>
                                    <es:sectorFunctionRef>SubNetwork=ONRM_RootMo_R,SubNetwork=eNB_CH,MeContext=RN_CH0001,ManagedElement=RN_CH0001,vsDataNodeSupport=1,vsDataSectorEquipmentFunction=S1C1</es:sectorFunctionRef>
                                    <es:radioTransmitPerformanceMode>0</es:radioTransmitPerformanceMode>
                                    <es:txPowerPersistentLock>false</es:txPowerPersistentLock>
                                    <es:configuredMaxTxPower>40000</es:configuredMaxTxPower>
                                    <es:zzzTemporary2></es:zzzTemporary2>
                                    <es:zzzTemporary1></es:zzzTemporary1>
                                    <es:zzzTemporary4>-2000000000</es:zzzTemporary4>
                                    <es:zzzTemporary3>-2000000000</es:zzzTemporary3>
                                    <es:zzzTemporary6>-2000000000</es:zzzTemporary6>
                                    <es:zzzTemporary5>-2000000000</es:zzzTemporary5>
                                    <es:virtualComChBeamfrmWtsPhase>0</es:virtualComChBeamfrmWtsPhase>
                                    <es:virtualComChBeamfrmWtsPhase>0</es:virtualComChBeamfrmWtsPhase>
                                    <es:virtualComChBeamfrmWtsPhase>0</es:virtualComChBeamfrmWtsPhase>
                                    <es:virtualComChBeamfrmWtsPhase>0</es:virtualComChBeamfrmWtsPhase>
                                    <es:virtualComChBeamfrmWtsPhase>0</es:virtualComChBeamfrmWtsPhase>
                                    <es:virtualComChBeamfrmWtsPhase>0</es:virtualComChBeamfrmWtsPhase>
                                    <es:virtualComChBeamfrmWtsPhase>0</es:virtualComChBeamfrmWtsPhase>
                                    <es:virtualComChBeamfrmWtsPhase>0</es:virtualComChBeamfrmWtsPhase>
                                    <es:virtualComChBeamfrmWtsAmplitude>0</es:virtualComChBeamfrmWtsAmplitude>
                                    <es:virtualComChBeamfrmWtsAmplitude>0</es:virtualComChBeamfrmWtsAmplitude>
                                    <es:virtualComChBeamfrmWtsAmplitude>0</es:virtualComChBeamfrmWtsAmplitude>
                                    <es:virtualComChBeamfrmWtsAmplitude>0</es:virtualComChBeamfrmWtsAmplitude>
                                    <es:virtualComChBeamfrmWtsAmplitude>0</es:virtualComChBeamfrmWtsAmplitude>
                                    <es:virtualComChBeamfrmWtsAmplitude>0</es:virtualComChBeamfrmWtsAmplitude>
                                    <es:virtualComChBeamfrmWtsAmplitude>0</es:virtualComChBeamfrmWtsAmplitude>
                                    <es:virtualComChBeamfrmWtsAmplitude>0</es:virtualComChBeamfrmWtsAmplitude>
                                    <es:microSleepTxActivation>false</es:microSleepTxActivation>
                                    <es:virtualSector>false</es:virtualSector>
                                    <es:sectorShape>0</es:sectorShape>
                                    <es:digitalTilt>0</es:digitalTilt>
                                    </es:vsDataSectorCarrier>
                                </xn:attributes>
                            </xn:VsDataContainer>
                            <xn:VsDataContainer id="2">
                                <xn:attributes>
                                    <xn:vsDataType>vsDataSectorCarrier</xn:vsDataType>
                                    <xn:vsDataFormatVersion>EricssonSpecificAttributes.17.28</xn:vsDataFormatVersion>
                                    <es:vsDataSectorCarrier>
                                    <es:noOfTxAntennas>4</es:noOfTxAntennas>
                                    <es:maximumTransmissionPower>487</es:maximumTransmissionPower>
                                    <es:prsEnabled>true</es:prsEnabled>
                                    <es:rfBranchTxRef></es:rfBranchTxRef>
                                    <es:noOfRxAntennas>4</es:noOfRxAntennas>
                                    <es:rfBranchRxRef></es:rfBranchRxRef>
                                    <es:ulForcedTimingAdvanceCommand>0</es:ulForcedTimingAdvanceCommand>
                                    <es:reservedBy>SubNetwork=ONRM_RootMo_R,SubNetwork=eNB_CH,MeContext=RN_CH0001,ManagedElement=RN_CH0001,vsDataENodeBFunction=1,vsDataEUtranCellFDD=CH0001L23</es:reservedBy>
                                    <es:sectorFunctionRef>SubNetwork=ONRM_RootMo_R,SubNetwork=eNB_CH,MeContext=RN_CH0001,ManagedElement=RN_CH0001,vsDataNodeSupport=1,vsDataSectorEquipmentFunction=S2C1</es:sectorFunctionRef>
                                    <es:radioTransmitPerformanceMode>0</es:radioTransmitPerformanceMode>
                                    <es:txPowerPersistentLock>false</es:txPowerPersistentLock>
                                    <es:configuredMaxTxPower>80000</es:configuredMaxTxPower>
                                    <es:zzzTemporary2></es:zzzTemporary2>
                                    <es:zzzTemporary1></es:zzzTemporary1>
                                    <es:zzzTemporary4>-2000000000</es:zzzTemporary4>
                                    <es:zzzTemporary3>-2000000000</es:zzzTemporary3>
                                    <es:zzzTemporary6>-2000000000</es:zzzTemporary6>
                                    <es:zzzTemporary5>-2000000000</es:zzzTemporary5>
                                    <es:virtualComChBeamfrmWtsPhase>0</es:virtualComChBeamfrmWtsPhase>
                                    <es:virtualComChBeamfrmWtsPhase>0</es:virtualComChBeamfrmWtsPhase>
                                    <es:virtualComChBeamfrmWtsPhase>0</es:virtualComChBeamfrmWtsPhase>
                                    <es:virtualComChBeamfrmWtsPhase>0</es:virtualComChBeamfrmWtsPhase>
                                    <es:virtualComChBeamfrmWtsPhase>0</es:virtualComChBeamfrmWtsPhase>
                                    <es:virtualComChBeamfrmWtsPhase>0</es:virtualComChBeamfrmWtsPhase>
                                    <es:virtualComChBeamfrmWtsPhase>0</es:virtualComChBeamfrmWtsPhase>
                                    <es:virtualComChBeamfrmWtsPhase>0</es:virtualComChBeamfrmWtsPhase>
                                    <es:virtualComChBeamfrmWtsAmplitude>0</es:virtualComChBeamfrmWtsAmplitude>
                                    <es:virtualComChBeamfrmWtsAmplitude>0</es:virtualComChBeamfrmWtsAmplitude>
                                    <es:virtualComChBeamfrmWtsAmplitude>0</es:virtualComChBeamfrmWtsAmplitude>
                                    <es:virtualComChBeamfrmWtsAmplitude>0</es:virtualComChBeamfrmWtsAmplitude>
                                    <es:virtualComChBeamfrmWtsAmplitude>0</es:virtualComChBeamfrmWtsAmplitude>
                                    <es:virtualComChBeamfrmWtsAmplitude>0</es:virtualComChBeamfrmWtsAmplitude>
                                    <es:virtualComChBeamfrmWtsAmplitude>0</es:virtualComChBeamfrmWtsAmplitude>
                                    <es:virtualComChBeamfrmWtsAmplitude>0</es:virtualComChBeamfrmWtsAmplitude>
                                    <es:microSleepTxActivation>false</es:microSleepTxActivation>
                                    <es:virtualSector>false</es:virtualSector>
                                    <es:sectorShape>0</es:sectorShape>
                                    <es:digitalTilt>0</es:digitalTilt>
                                    </es:vsDataSectorCarrier>
                                </xn:attributes>
                            </xn:VsDataContainer>
                            <xn:VsDataContainer id="3">
                                <xn:attributes>
                                    <xn:vsDataType>vsDataSectorCarrier</xn:vsDataType>
                                    <xn:vsDataFormatVersion>EricssonSpecificAttributes.17.28</xn:vsDataFormatVersion>
                                    <es:vsDataSectorCarrier>
                                    <es:noOfTxAntennas>2</es:noOfTxAntennas>
                                    <es:maximumTransmissionPower>457</es:maximumTransmissionPower>
                                    <es:prsEnabled>true</es:prsEnabled>
                                    <es:rfBranchTxRef></es:rfBranchTxRef>
                                    <es:noOfRxAntennas>2</es:noOfRxAntennas>
                                    <es:rfBranchRxRef></es:rfBranchRxRef>
                                    <es:ulForcedTimingAdvanceCommand>0</es:ulForcedTimingAdvanceCommand>
                                    <es:reservedBy>SubNetwork=ONRM_RootMo_R,SubNetwork=eNB_CH,MeContext=RN_CH0001,ManagedElement=RN_CH0001,vsDataENodeBFunction=1,vsDataEUtranCellFDD=CH0001L33</es:reservedBy>
                                    <es:sectorFunctionRef>SubNetwork=ONRM_RootMo_R,SubNetwork=eNB_CH,MeContext=RN_CH0001,ManagedElement=RN_CH0001,vsDataNodeSupport=1,vsDataSectorEquipmentFunction=S3C1</es:sectorFunctionRef>
                                    <es:radioTransmitPerformanceMode>0</es:radioTransmitPerformanceMode>
                                    <es:txPowerPersistentLock>false</es:txPowerPersistentLock>
                                    <es:configuredMaxTxPower>40000</es:configuredMaxTxPower>
                                    <es:zzzTemporary2></es:zzzTemporary2>
                                    <es:zzzTemporary1></es:zzzTemporary1>
                                    <es:zzzTemporary4>-2000000000</es:zzzTemporary4>
                                    <es:zzzTemporary3>-2000000000</es:zzzTemporary3>
                                    <es:zzzTemporary6>-2000000000</es:zzzTemporary6>
                                    <es:zzzTemporary5>-2000000000</es:zzzTemporary5>
                                    <es:virtualComChBeamfrmWtsPhase>0</es:virtualComChBeamfrmWtsPhase>
                                    <es:virtualComChBeamfrmWtsPhase>0</es:virtualComChBeamfrmWtsPhase>
                                    <es:virtualComChBeamfrmWtsPhase>0</es:virtualComChBeamfrmWtsPhase>
                                    <es:virtualComChBeamfrmWtsPhase>0</es:virtualComChBeamfrmWtsPhase>
                                    <es:virtualComChBeamfrmWtsPhase>0</es:virtualComChBeamfrmWtsPhase>
                                    <es:virtualComChBeamfrmWtsPhase>0</es:virtualComChBeamfrmWtsPhase>
                                    <es:virtualComChBeamfrmWtsPhase>0</es:virtualComChBeamfrmWtsPhase>
                                    <es:virtualComChBeamfrmWtsPhase>0</es:virtualComChBeamfrmWtsPhase>
                                    <es:virtualComChBeamfrmWtsAmplitude>0</es:virtualComChBeamfrmWtsAmplitude>
                                    <es:virtualComChBeamfrmWtsAmplitude>0</es:virtualComChBeamfrmWtsAmplitude>
                                    <es:virtualComChBeamfrmWtsAmplitude>0</es:virtualComChBeamfrmWtsAmplitude>
                                    <es:virtualComChBeamfrmWtsAmplitude>0</es:virtualComChBeamfrmWtsAmplitude>
                                    <es:virtualComChBeamfrmWtsAmplitude>0</es:virtualComChBeamfrmWtsAmplitude>
                                    <es:virtualComChBeamfrmWtsAmplitude>0</es:virtualComChBeamfrmWtsAmplitude>
                                    <es:virtualComChBeamfrmWtsAmplitude>0</es:virtualComChBeamfrmWtsAmplitude>
                                    <es:virtualComChBeamfrmWtsAmplitude>0</es:virtualComChBeamfrmWtsAmplitude>
                                    <es:microSleepTxActivation>false</es:microSleepTxActivation>
                                    <es:virtualSector>false</es:virtualSector>
                                    <es:sectorShape>0</es:sectorShape>
                                    <es:digitalTilt>0</es:digitalTilt>
                                    </es:vsDataSectorCarrier>
                                </xn:attributes>
                            </xn:VsDataContainer>
                            <xn:VsDataContainer id="5">
                                <xn:attributes>
                                    <xn:vsDataType>vsDataSectorCarrier</xn:vsDataType>
                                    <xn:vsDataFormatVersion>EricssonSpecificAttributes.17.28</xn:vsDataFormatVersion>
                                    <es:vsDataSectorCarrier>
                                    <es:noOfTxAntennas>2</es:noOfTxAntennas>
                                    <es:maximumTransmissionPower>457</es:maximumTransmissionPower>
                                    <es:prsEnabled>true</es:prsEnabled>
                                    <es:rfBranchTxRef></es:rfBranchTxRef>
                                    <es:noOfRxAntennas>2</es:noOfRxAntennas>
                                    <es:rfBranchRxRef></es:rfBranchRxRef>
                                    <es:ulForcedTimingAdvanceCommand>0</es:ulForcedTimingAdvanceCommand>
                                    <es:reservedBy>SubNetwork=ONRM_RootMo_R,SubNetwork=eNB_CH,MeContext=RN_CH0001,ManagedElement=RN_CH0001,vsDataENodeBFunction=1,vsDataEUtranCellFDD=CH0001L14</es:reservedBy>
                                    <es:reservedBy>SubNetwork=ONRM_RootMo_R,SubNetwork=eNB_CH,MeContext=RN_CH0001,ManagedElement=RN_CH0001,vsDataENodeBFunction=1,vsDataUlCompGroup=2</es:reservedBy>
                                    <es:sectorFunctionRef>SubNetwork=ONRM_RootMo_R,SubNetwork=eNB_CH,MeContext=RN_CH0001,ManagedElement=RN_CH0001,vsDataNodeSupport=1,vsDataSectorEquipmentFunction=S1C1</es:sectorFunctionRef>
                                    <es:radioTransmitPerformanceMode>0</es:radioTransmitPerformanceMode>
                                    <es:txPowerPersistentLock>false</es:txPowerPersistentLock>
                                    <es:configuredMaxTxPower>40000</es:configuredMaxTxPower>
                                    <es:zzzTemporary2></es:zzzTemporary2>
                                    <es:zzzTemporary1></es:zzzTemporary1>
                                    <es:zzzTemporary4>-2000000000</es:zzzTemporary4>
                                    <es:zzzTemporary3>-2000000000</es:zzzTemporary3>
                                    <es:zzzTemporary6>-2000000000</es:zzzTemporary6>
                                    <es:zzzTemporary5>-2000000000</es:zzzTemporary5>
                                    <es:virtualComChBeamfrmWtsPhase>0</es:virtualComChBeamfrmWtsPhase>
                                    <es:virtualComChBeamfrmWtsPhase>0</es:virtualComChBeamfrmWtsPhase>
                                    <es:virtualComChBeamfrmWtsPhase>0</es:virtualComChBeamfrmWtsPhase>
                                    <es:virtualComChBeamfrmWtsPhase>0</es:virtualComChBeamfrmWtsPhase>
                                    <es:virtualComChBeamfrmWtsPhase>0</es:virtualComChBeamfrmWtsPhase>
                                    <es:virtualComChBeamfrmWtsPhase>0</es:virtualComChBeamfrmWtsPhase>
                                    <es:virtualComChBeamfrmWtsPhase>0</es:virtualComChBeamfrmWtsPhase>
                                    <es:virtualComChBeamfrmWtsPhase>0</es:virtualComChBeamfrmWtsPhase>
                                    <es:virtualComChBeamfrmWtsAmplitude>0</es:virtualComChBeamfrmWtsAmplitude>
                                    <es:virtualComChBeamfrmWtsAmplitude>0</es:virtualComChBeamfrmWtsAmplitude>
                                    <es:virtualComChBeamfrmWtsAmplitude>0</es:virtualComChBeamfrmWtsAmplitude>
                                    <es:virtualComChBeamfrmWtsAmplitude>0</es:virtualComChBeamfrmWtsAmplitude>
                                    <es:virtualComChBeamfrmWtsAmplitude>0</es:virtualComChBeamfrmWtsAmplitude>
                                    <es:virtualComChBeamfrmWtsAmplitude>0</es:virtualComChBeamfrmWtsAmplitude>
                                    <es:virtualComChBeamfrmWtsAmplitude>0</es:virtualComChBeamfrmWtsAmplitude>
                                    <es:virtualComChBeamfrmWtsAmplitude>0</es:virtualComChBeamfrmWtsAmplitude>
                                    <es:microSleepTxActivation>false</es:microSleepTxActivation>
                                    <es:virtualSector>false</es:virtualSector>
                                    <es:sectorShape>0</es:sectorShape>
                                    <es:digitalTilt>0</es:digitalTilt>
                                    </es:vsDataSectorCarrier>
                                </xn:attributes>
                            </xn:VsDataContainer>
                            <xn:VsDataContainer id="6">
                                <xn:attributes>
                                    <xn:vsDataType>vsDataSectorCarrier</xn:vsDataType>
                                    <xn:vsDataFormatVersion>EricssonSpecificAttributes.17.28</xn:vsDataFormatVersion>
                                    <es:vsDataSectorCarrier>
                                    <es:noOfTxAntennas>4</es:noOfTxAntennas>
                                    <es:maximumTransmissionPower>487</es:maximumTransmissionPower>
                                    <es:prsEnabled>true</es:prsEnabled>
                                    <es:rfBranchTxRef></es:rfBranchTxRef>
                                    <es:noOfRxAntennas>4</es:noOfRxAntennas>
                                    <es:rfBranchRxRef></es:rfBranchRxRef>
                                    <es:ulForcedTimingAdvanceCommand>0</es:ulForcedTimingAdvanceCommand>
                                    <es:reservedBy>SubNetwork=ONRM_RootMo_R,SubNetwork=eNB_CH,MeContext=RN_CH0001,ManagedElement=RN_CH0001,vsDataENodeBFunction=1,vsDataEUtranCellFDD=CH0001L24</es:reservedBy>
                                    <es:reservedBy>SubNetwork=ONRM_RootMo_R,SubNetwork=eNB_CH,MeContext=RN_CH0001,ManagedElement=RN_CH0001,vsDataENodeBFunction=1,vsDataUlCompGroup=2</es:reservedBy>
                                    <es:sectorFunctionRef>SubNetwork=ONRM_RootMo_R,SubNetwork=eNB_CH,MeContext=RN_CH0001,ManagedElement=RN_CH0001,vsDataNodeSupport=1,vsDataSectorEquipmentFunction=S2C1</es:sectorFunctionRef>
                                    <es:radioTransmitPerformanceMode>0</es:radioTransmitPerformanceMode>
                                    <es:txPowerPersistentLock>false</es:txPowerPersistentLock>
                                    <es:configuredMaxTxPower>80000</es:configuredMaxTxPower>
                                    <es:zzzTemporary2></es:zzzTemporary2>
                                    <es:zzzTemporary1></es:zzzTemporary1>
                                    <es:zzzTemporary4>-2000000000</es:zzzTemporary4>
                                    <es:zzzTemporary3>-2000000000</es:zzzTemporary3>
                                    <es:zzzTemporary6>-2000000000</es:zzzTemporary6>
                                    <es:zzzTemporary5>-2000000000</es:zzzTemporary5>
                                    <es:virtualComChBeamfrmWtsPhase>0</es:virtualComChBeamfrmWtsPhase>
                                    <es:virtualComChBeamfrmWtsPhase>0</es:virtualComChBeamfrmWtsPhase>
                                    <es:virtualComChBeamfrmWtsPhase>0</es:virtualComChBeamfrmWtsPhase>
                                    <es:virtualComChBeamfrmWtsPhase>0</es:virtualComChBeamfrmWtsPhase>
                                    <es:virtualComChBeamfrmWtsPhase>0</es:virtualComChBeamfrmWtsPhase>
                                    <es:virtualComChBeamfrmWtsPhase>0</es:virtualComChBeamfrmWtsPhase>
                                    <es:virtualComChBeamfrmWtsPhase>0</es:virtualComChBeamfrmWtsPhase>
                                    <es:virtualComChBeamfrmWtsPhase>0</es:virtualComChBeamfrmWtsPhase>
                                    <es:virtualComChBeamfrmWtsAmplitude>0</es:virtualComChBeamfrmWtsAmplitude>
                                    <es:virtualComChBeamfrmWtsAmplitude>0</es:virtualComChBeamfrmWtsAmplitude>
                                    <es:virtualComChBeamfrmWtsAmplitude>0</es:virtualComChBeamfrmWtsAmplitude>
                                    <es:virtualComChBeamfrmWtsAmplitude>0</es:virtualComChBeamfrmWtsAmplitude>
                                    <es:virtualComChBeamfrmWtsAmplitude>0</es:virtualComChBeamfrmWtsAmplitude>
                                    <es:virtualComChBeamfrmWtsAmplitude>0</es:virtualComChBeamfrmWtsAmplitude>
                                    <es:virtualComChBeamfrmWtsAmplitude>0</es:virtualComChBeamfrmWtsAmplitude>
                                    <es:virtualComChBeamfrmWtsAmplitude>0</es:virtualComChBeamfrmWtsAmplitude>
                                    <es:microSleepTxActivation>false</es:microSleepTxActivation>
                                    <es:virtualSector>false</es:virtualSector>
                                    <es:sectorShape>0</es:sectorShape>
                                    <es:digitalTilt>0</es:digitalTilt>
                                    </es:vsDataSectorCarrier>
                                </xn:attributes>
                            </xn:VsDataContainer>
                            <xn:VsDataContainer id="7">
                                <xn:attributes>
                                    <xn:vsDataType>vsDataSectorCarrier</xn:vsDataType>
                                    <xn:vsDataFormatVersion>EricssonSpecificAttributes.17.28</xn:vsDataFormatVersion>
                                    <es:vsDataSectorCarrier>
                                    <es:noOfTxAntennas>2</es:noOfTxAntennas>
                                    <es:maximumTransmissionPower>457</es:maximumTransmissionPower>
                                    <es:prsEnabled>true</es:prsEnabled>
                                    <es:rfBranchTxRef></es:rfBranchTxRef>
                                    <es:noOfRxAntennas>2</es:noOfRxAntennas>
                                    <es:rfBranchRxRef></es:rfBranchRxRef>
                                    <es:ulForcedTimingAdvanceCommand>0</es:ulForcedTimingAdvanceCommand>
                                    <es:reservedBy>SubNetwork=ONRM_RootMo_R,SubNetwork=eNB_CH,MeContext=RN_CH0001,ManagedElement=RN_CH0001,vsDataENodeBFunction=1,vsDataEUtranCellFDD=CH0001L34</es:reservedBy>
                                    <es:reservedBy>SubNetwork=ONRM_RootMo_R,SubNetwork=eNB_CH,MeContext=RN_CH0001,ManagedElement=RN_CH0001,vsDataENodeBFunction=1,vsDataUlCompGroup=2</es:reservedBy>
                                    <es:sectorFunctionRef>SubNetwork=ONRM_RootMo_R,SubNetwork=eNB_CH,MeContext=RN_CH0001,ManagedElement=RN_CH0001,vsDataNodeSupport=1,vsDataSectorEquipmentFunction=S3C1</es:sectorFunctionRef>
                                    <es:radioTransmitPerformanceMode>0</es:radioTransmitPerformanceMode>
                                    <es:txPowerPersistentLock>false</es:txPowerPersistentLock>
                                    <es:configuredMaxTxPower>40000</es:configuredMaxTxPower>
                                    <es:zzzTemporary2></es:zzzTemporary2>
                                    <es:zzzTemporary1></es:zzzTemporary1>
                                    <es:zzzTemporary4>-2000000000</es:zzzTemporary4>
                                    <es:zzzTemporary3>-2000000000</es:zzzTemporary3>
                                    <es:zzzTemporary6>-2000000000</es:zzzTemporary6>
                                    <es:zzzTemporary5>-2000000000</es:zzzTemporary5>
                                    <es:virtualComChBeamfrmWtsPhase>0</es:virtualComChBeamfrmWtsPhase>
                                    <es:virtualComChBeamfrmWtsPhase>0</es:virtualComChBeamfrmWtsPhase>
                                    <es:virtualComChBeamfrmWtsPhase>0</es:virtualComChBeamfrmWtsPhase>
                                    <es:virtualComChBeamfrmWtsPhase>0</es:virtualComChBeamfrmWtsPhase>
                                    <es:virtualComChBeamfrmWtsPhase>0</es:virtualComChBeamfrmWtsPhase>
                                    <es:virtualComChBeamfrmWtsPhase>0</es:virtualComChBeamfrmWtsPhase>
                                    <es:virtualComChBeamfrmWtsPhase>0</es:virtualComChBeamfrmWtsPhase>
                                    <es:virtualComChBeamfrmWtsPhase>0</es:virtualComChBeamfrmWtsPhase>
                                    <es:virtualComChBeamfrmWtsAmplitude>0</es:virtualComChBeamfrmWtsAmplitude>
                                    <es:virtualComChBeamfrmWtsAmplitude>0</es:virtualComChBeamfrmWtsAmplitude>
                                    <es:virtualComChBeamfrmWtsAmplitude>0</es:virtualComChBeamfrmWtsAmplitude>
                                    <es:virtualComChBeamfrmWtsAmplitude>0</es:virtualComChBeamfrmWtsAmplitude>
                                    <es:virtualComChBeamfrmWtsAmplitude>0</es:virtualComChBeamfrmWtsAmplitude>
                                    <es:virtualComChBeamfrmWtsAmplitude>0</es:virtualComChBeamfrmWtsAmplitude>
                                    <es:virtualComChBeamfrmWtsAmplitude>0</es:virtualComChBeamfrmWtsAmplitude>
                                    <es:virtualComChBeamfrmWtsAmplitude>0</es:virtualComChBeamfrmWtsAmplitude>
                                    <es:microSleepTxActivation>false</es:microSleepTxActivation>
                                    <es:virtualSector>false</es:virtualSector>
                                    <es:sectorShape>0</es:sectorShape>
                                    <es:digitalTilt>0</es:digitalTilt>
                                    </es:vsDataSectorCarrier>
                                </xn:attributes>
                            </xn:VsDataContainer>
                            <xn:VsDataContainer id="CH0001L11">
                                <xn:attributes>
                                    <xn:vsDataType>vsDataSectorCarrier</xn:vsDataType>
                                    <xn:vsDataFormatVersion>EricssonSpecificAttributes.17.28</xn:vsDataFormatVersion>
                                    <es:vsDataSectorCarrier>
                                    <es:noOfTxAntennas>2</es:noOfTxAntennas>
                                    <es:maximumTransmissionPower>425</es:maximumTransmissionPower>
                                    <es:prsEnabled>true</es:prsEnabled>
                                    <es:rfBranchTxRef></es:rfBranchTxRef>
                                    <es:noOfRxAntennas>2</es:noOfRxAntennas>
                                    <es:rfBranchRxRef></es:rfBranchRxRef>
                                    <es:ulForcedTimingAdvanceCommand>0</es:ulForcedTimingAdvanceCommand>
                                    <es:reservedBy>SubNetwork=ONRM_RootMo_R,SubNetwork=eNB_CH,MeContext=RN_CH0001,ManagedElement=RN_CH0001,vsDataENodeBFunction=1,vsDataEUtranCellFDD=CH0001L11</es:reservedBy>
                                    <es:sectorFunctionRef>SubNetwork=ONRM_RootMo_R,SubNetwork=eNB_CH,MeContext=RN_CH0001,ManagedElement=RN_CH0001,vsDataNodeSupport=1,vsDataSectorEquipmentFunction=S1B3</es:sectorFunctionRef>
                                    <es:radioTransmitPerformanceMode>2</es:radioTransmitPerformanceMode>
                                    <es:txPowerPersistentLock>false</es:txPowerPersistentLock>
                                    <es:configuredMaxTxPower>40000</es:configuredMaxTxPower>
                                    <es:zzzTemporary2></es:zzzTemporary2>
                                    <es:zzzTemporary1></es:zzzTemporary1>
                                    <es:zzzTemporary4>-2000000000</es:zzzTemporary4>
                                    <es:zzzTemporary3>-2000000000</es:zzzTemporary3>
                                    <es:zzzTemporary6>-2000000000</es:zzzTemporary6>
                                    <es:zzzTemporary5>-2000000000</es:zzzTemporary5>
                                    <es:virtualComChBeamfrmWtsPhase>0</es:virtualComChBeamfrmWtsPhase>
                                    <es:virtualComChBeamfrmWtsPhase>0</es:virtualComChBeamfrmWtsPhase>
                                    <es:virtualComChBeamfrmWtsPhase>0</es:virtualComChBeamfrmWtsPhase>
                                    <es:virtualComChBeamfrmWtsPhase>0</es:virtualComChBeamfrmWtsPhase>
                                    <es:virtualComChBeamfrmWtsPhase>0</es:virtualComChBeamfrmWtsPhase>
                                    <es:virtualComChBeamfrmWtsPhase>0</es:virtualComChBeamfrmWtsPhase>
                                    <es:virtualComChBeamfrmWtsPhase>0</es:virtualComChBeamfrmWtsPhase>
                                    <es:virtualComChBeamfrmWtsPhase>0</es:virtualComChBeamfrmWtsPhase>
                                    <es:virtualComChBeamfrmWtsAmplitude>0</es:virtualComChBeamfrmWtsAmplitude>
                                    <es:virtualComChBeamfrmWtsAmplitude>0</es:virtualComChBeamfrmWtsAmplitude>
                                    <es:virtualComChBeamfrmWtsAmplitude>0</es:virtualComChBeamfrmWtsAmplitude>
                                    <es:virtualComChBeamfrmWtsAmplitude>0</es:virtualComChBeamfrmWtsAmplitude>
                                    <es:virtualComChBeamfrmWtsAmplitude>0</es:virtualComChBeamfrmWtsAmplitude>
                                    <es:virtualComChBeamfrmWtsAmplitude>0</es:virtualComChBeamfrmWtsAmplitude>
                                    <es:virtualComChBeamfrmWtsAmplitude>0</es:virtualComChBeamfrmWtsAmplitude>
                                    <es:virtualComChBeamfrmWtsAmplitude>0</es:virtualComChBeamfrmWtsAmplitude>
                                    <es:microSleepTxActivation>false</es:microSleepTxActivation>
                                    <es:virtualSector>false</es:virtualSector>
                                    <es:sectorShape>0</es:sectorShape>
                                    <es:digitalTilt>0</es:digitalTilt>
                                    </es:vsDataSectorCarrier>
                                </xn:attributes>
                            </xn:VsDataContainer>
                            <xn:VsDataContainer id="CH0001L21">
                                <xn:attributes>
                                    <xn:vsDataType>vsDataSectorCarrier</xn:vsDataType>
                                    <xn:vsDataFormatVersion>EricssonSpecificAttributes.17.28</xn:vsDataFormatVersion>
                                    <es:vsDataSectorCarrier>
                                    <es:noOfTxAntennas>2</es:noOfTxAntennas>
                                    <es:maximumTransmissionPower>425</es:maximumTransmissionPower>
                                    <es:prsEnabled>true</es:prsEnabled>
                                    <es:rfBranchTxRef></es:rfBranchTxRef>
                                    <es:noOfRxAntennas>2</es:noOfRxAntennas>
                                    <es:rfBranchRxRef></es:rfBranchRxRef>
                                    <es:ulForcedTimingAdvanceCommand>0</es:ulForcedTimingAdvanceCommand>
                                    <es:reservedBy>SubNetwork=ONRM_RootMo_R,SubNetwork=eNB_CH,MeContext=RN_CH0001,ManagedElement=RN_CH0001,vsDataENodeBFunction=1,vsDataEUtranCellFDD=CH0001L21</es:reservedBy>
                                    <es:sectorFunctionRef>SubNetwork=ONRM_RootMo_R,SubNetwork=eNB_CH,MeContext=RN_CH0001,ManagedElement=RN_CH0001,vsDataNodeSupport=1,vsDataSectorEquipmentFunction=S2B3</es:sectorFunctionRef>
                                    <es:radioTransmitPerformanceMode>2</es:radioTransmitPerformanceMode>
                                    <es:txPowerPersistentLock>false</es:txPowerPersistentLock>
                                    <es:configuredMaxTxPower>40000</es:configuredMaxTxPower>
                                    <es:zzzTemporary2></es:zzzTemporary2>
                                    <es:zzzTemporary1></es:zzzTemporary1>
                                    <es:zzzTemporary4>-2000000000</es:zzzTemporary4>
                                    <es:zzzTemporary3>-2000000000</es:zzzTemporary3>
                                    <es:zzzTemporary6>-2000000000</es:zzzTemporary6>
                                    <es:zzzTemporary5>-2000000000</es:zzzTemporary5>
                                    <es:virtualComChBeamfrmWtsPhase>0</es:virtualComChBeamfrmWtsPhase>
                                    <es:virtualComChBeamfrmWtsPhase>0</es:virtualComChBeamfrmWtsPhase>
                                    <es:virtualComChBeamfrmWtsPhase>0</es:virtualComChBeamfrmWtsPhase>
                                    <es:virtualComChBeamfrmWtsPhase>0</es:virtualComChBeamfrmWtsPhase>
                                    <es:virtualComChBeamfrmWtsPhase>0</es:virtualComChBeamfrmWtsPhase>
                                    <es:virtualComChBeamfrmWtsPhase>0</es:virtualComChBeamfrmWtsPhase>
                                    <es:virtualComChBeamfrmWtsPhase>0</es:virtualComChBeamfrmWtsPhase>
                                    <es:virtualComChBeamfrmWtsPhase>0</es:virtualComChBeamfrmWtsPhase>
                                    <es:virtualComChBeamfrmWtsAmplitude>0</es:virtualComChBeamfrmWtsAmplitude>
                                    <es:virtualComChBeamfrmWtsAmplitude>0</es:virtualComChBeamfrmWtsAmplitude>
                                    <es:virtualComChBeamfrmWtsAmplitude>0</es:virtualComChBeamfrmWtsAmplitude>
                                    <es:virtualComChBeamfrmWtsAmplitude>0</es:virtualComChBeamfrmWtsAmplitude>
                                    <es:virtualComChBeamfrmWtsAmplitude>0</es:virtualComChBeamfrmWtsAmplitude>
                                    <es:virtualComChBeamfrmWtsAmplitude>0</es:virtualComChBeamfrmWtsAmplitude>
                                    <es:virtualComChBeamfrmWtsAmplitude>0</es:virtualComChBeamfrmWtsAmplitude>
                                    <es:virtualComChBeamfrmWtsAmplitude>0</es:virtualComChBeamfrmWtsAmplitude>
                                    <es:microSleepTxActivation>false</es:microSleepTxActivation>
                                    <es:virtualSector>false</es:virtualSector>
                                    <es:sectorShape>0</es:sectorShape>
                                    <es:digitalTilt>0</es:digitalTilt>
                                    </es:vsDataSectorCarrier>
                                </xn:attributes>
                            </xn:VsDataContainer>
                            <xn:VsDataContainer id="CH0001L31">
                                <xn:attributes>
                                    <xn:vsDataType>vsDataSectorCarrier</xn:vsDataType>
                                    <xn:vsDataFormatVersion>EricssonSpecificAttributes.17.28</xn:vsDataFormatVersion>
                                    <es:vsDataSectorCarrier>
                                    <es:noOfTxAntennas>2</es:noOfTxAntennas>
                                    <es:maximumTransmissionPower>425</es:maximumTransmissionPower>
                                    <es:prsEnabled>true</es:prsEnabled>
                                    <es:rfBranchTxRef></es:rfBranchTxRef>
                                    <es:noOfRxAntennas>2</es:noOfRxAntennas>
                                    <es:rfBranchRxRef></es:rfBranchRxRef>
                                    <es:ulForcedTimingAdvanceCommand>0</es:ulForcedTimingAdvanceCommand>
                                    <es:reservedBy>SubNetwork=ONRM_RootMo_R,SubNetwork=eNB_CH,MeContext=RN_CH0001,ManagedElement=RN_CH0001,vsDataENodeBFunction=1,vsDataEUtranCellFDD=CH0001L31</es:reservedBy>
                                    <es:sectorFunctionRef>SubNetwork=ONRM_RootMo_R,SubNetwork=eNB_CH,MeContext=RN_CH0001,ManagedElement=RN_CH0001,vsDataNodeSupport=1,vsDataSectorEquipmentFunction=S3B3</es:sectorFunctionRef>
                                    <es:radioTransmitPerformanceMode>2</es:radioTransmitPerformanceMode>
                                    <es:txPowerPersistentLock>false</es:txPowerPersistentLock>
                                    <es:configuredMaxTxPower>40000</es:configuredMaxTxPower>
                                    <es:zzzTemporary2></es:zzzTemporary2>
                                    <es:zzzTemporary1></es:zzzTemporary1>
                                    <es:zzzTemporary4>-2000000000</es:zzzTemporary4>
                                    <es:zzzTemporary3>-2000000000</es:zzzTemporary3>
                                    <es:zzzTemporary6>-2000000000</es:zzzTemporary6>
                                    <es:zzzTemporary5>-2000000000</es:zzzTemporary5>
                                    <es:virtualComChBeamfrmWtsPhase>0</es:virtualComChBeamfrmWtsPhase>
                                    <es:virtualComChBeamfrmWtsPhase>0</es:virtualComChBeamfrmWtsPhase>
                                    <es:virtualComChBeamfrmWtsPhase>0</es:virtualComChBeamfrmWtsPhase>
                                    <es:virtualComChBeamfrmWtsPhase>0</es:virtualComChBeamfrmWtsPhase>
                                    <es:virtualComChBeamfrmWtsPhase>0</es:virtualComChBeamfrmWtsPhase>
                                    <es:virtualComChBeamfrmWtsPhase>0</es:virtualComChBeamfrmWtsPhase>
                                    <es:virtualComChBeamfrmWtsPhase>0</es:virtualComChBeamfrmWtsPhase>
                                    <es:virtualComChBeamfrmWtsPhase>0</es:virtualComChBeamfrmWtsPhase>
                                    <es:virtualComChBeamfrmWtsAmplitude>0</es:virtualComChBeamfrmWtsAmplitude>
                                    <es:virtualComChBeamfrmWtsAmplitude>0</es:virtualComChBeamfrmWtsAmplitude>
                                    <es:virtualComChBeamfrmWtsAmplitude>0</es:virtualComChBeamfrmWtsAmplitude>
                                    <es:virtualComChBeamfrmWtsAmplitude>0</es:virtualComChBeamfrmWtsAmplitude>
                                    <es:virtualComChBeamfrmWtsAmplitude>0</es:virtualComChBeamfrmWtsAmplitude>
                                    <es:virtualComChBeamfrmWtsAmplitude>0</es:virtualComChBeamfrmWtsAmplitude>
                                    <es:virtualComChBeamfrmWtsAmplitude>0</es:virtualComChBeamfrmWtsAmplitude>
                                    <es:virtualComChBeamfrmWtsAmplitude>0</es:virtualComChBeamfrmWtsAmplitude>
                                    <es:microSleepTxActivation>false</es:microSleepTxActivation>
                                    <es:virtualSector>false</es:virtualSector>
                                    <es:sectorShape>0</es:sectorShape>
                                    <es:digitalTilt>0</es:digitalTilt>
                                    </es:vsDataSectorCarrier>
                                </xn:attributes>
                            </xn:VsDataContainer>
                        </xn:VsDataContainer>
                    </xn:ManagedElement>
                </xn:MeContext>
            </xn:SubNetwork>
        </xn:SubNetwork>
    </configData>
    <fileFooter dateTime="2018-07-18T19:26:18Z"/>
</bulkCmConfigDataFile>
